string_processing-0.1.2.dist-info/METADATA
string_processing-0.1.2.dist-info/WHEEL
string_processing/string_processing.pyi
string_processing/__init__.py
string_processing/__pycache__/__init__.cpython-311.pyc
string_processing/__pycache__/__init__.cpython-310.pyc
string_processing/string_processing.cpython-312-darwin.so
string_processing-0.1.2.dist-info/RECORD
