Metadata-Version: 2.1
Name: string_processing
Version: 0.1.2
Requires-Python: >=3.10
